[
  {
    "name": "participate",
    "trans": [],
    "usphone": "",
    "ukphone": ""
  },
  {
    "name": "fill out",
    "trans": [],
    "usphone": "",
    "ukphone": ""
  },
  {
    "name": "evaluate",
    "trans": [],
    "usphone": "",
    "ukphone": ""
  },
  {
    "name": "arrange",
    "trans": [],
    "usphone": "",
    "ukphone": ""
  },
  {
    "name": "chimpanzee",
    "trans": [],
    "usphone": "",
    "ukphone": ""
  },
  {
    "name": "dolphin",
    "trans": [],
    "usphone": "",
    "ukphone": ""
  },
  {
    "name": "sign",
    "trans": [],
    "usphone": "",
    "ukphone": ""
  },
  {
    "name": "hunt",
    "trans": [],
    "usphone": "",
    "ukphone": ""
  },
  {
    "name": "actor",
    "trans": [],
    "usphone": "",
    "ukphone": ""
  },
  {
    "name": "actress",
    "trans": [],
    "usphone": "",
    "ukphone": ""
  },
  {
    "name": "writer",
    "trans": [],
    "usphone": "",
    "ukphone": ""
  },
  {
    "name": "collection",
    "trans": [],
    "usphone": "",
    "ukphone": ""
  },
  {
    "name": "boxing",
    "trans": [],
    "usphone": "",
    "ukphone": ""
  },
  {
    "name": "ski",
    "trans": [],
    "usphone": "",
    "ukphone": ""
  },
  {
    "name": "water skiing",
    "trans": [],
    "usphone": "",
    "ukphone": ""
  },
  {
    "name": "windsurfing",
    "trans": [],
    "usphone": "",
    "ukphone": ""
  },
  {
    "name": "frightening",
    "trans": [],
    "usphone": "",
    "ukphone": ""
  },
  {
    "name": "underwater",
    "trans": [],
    "usphone": "",
    "ukphone": ""
  },
  {
    "name": "spirit",
    "trans": [],
    "usphone": "",
    "ukphone": ""
  },
  {
    "name": "explorer",
    "trans": [],
    "usphone": "",
    "ukphone": ""
  },
  {
    "name": "sailor",
    "trans": [],
    "usphone": "",
    "ukphone": ""
  },
  {
    "name": "Viking",
    "trans": [],
    "usphone": "",
    "ukphone": ""
  },
  {
    "name": "voyage",
    "trans": [],
    "usphone": "",
    "ukphone": ""
  },
  {
    "name": "ancestor",
    "trans": [],
    "usphone": "",
    "ukphone": ""
  },
  {
    "name": "set sail",
    "trans": [],
    "usphone": "",
    "ukphone": ""
  },
  {
    "name": "AD",
    "trans": [],
    "usphone": "",
    "ukphone": ""
  },
  {
    "name": "further",
    "trans": [],
    "usphone": "",
    "ukphone": ""
  },
  {
    "name": "according to",
    "trans": [],
    "usphone": "",
    "ukphone": ""
  },
  {
    "name": "get into trouble",
    "trans": [],
    "usphone": "",
    "ukphone": ""
  },
  {
    "name": "persuade",
    "trans": [],
    "usphone": "",
    "ukphone": ""
  },
  {
    "name": "make it to",
    "trans": [],
    "usphone": "",
    "ukphone": ""
  },
  {
    "name": "in search of",
    "trans": [],
    "usphone": "",
    "ukphone": ""
  },
  {
    "name": "unknown",
    "trans": [],
    "usphone": "",
    "ukphone": ""
  },
  {
    "name": "eventually",
    "trans": [],
    "usphone": "",
    "ukphone": ""
  },
  {
    "name": "present-day",
    "trans": [],
    "usphone": "",
    "ukphone": ""
  },
  {
    "name": "deed",
    "trans": [],
    "usphone": "",
    "ukphone": ""
  },
  {
    "name": "journey",
    "trans": [],
    "usphone": "",
    "ukphone": ""
  },
  {
    "name": "lecture",
    "trans": [],
    "usphone": "",
    "ukphone": ""
  },
  {
    "name": "brake",
    "trans": [],
    "usphone": "",
    "ukphone": ""
  },
  {
    "name": "apologise",
    "trans": [],
    "usphone": "",
    "ukphone": ""
  },
  {
    "name": "the Antarctic",
    "trans": [],
    "usphone": "",
    "ukphone": ""
  },
  {
    "name": "pollute",
    "trans": [],
    "usphone": "",
    "ukphone": ""
  },
  {
    "name": "pollution",
    "trans": [],
    "usphone": "",
    "ukphone": ""
  },
  {
    "name": "over-fishing",
    "trans": [],
    "usphone": "",
    "ukphone": ""
  },
  {
    "name": "industrial",
    "trans": [],
    "usphone": "",
    "ukphone": ""
  },
  {
    "name": "agricultural",
    "trans": [],
    "usphone": "",
    "ukphone": ""
  },
  {
    "name": "chemical",
    "trans": [],
    "usphone": "",
    "ukphone": ""
  },
  {
    "name": "ban",
    "trans": [],
    "usphone": "",
    "ukphone": ""
  },
  {
    "name": "altogether",
    "trans": [],
    "usphone": "",
    "ukphone": ""
  },
  {
    "name": "handle",
    "trans": [],
    "usphone": "",
    "ukphone": ""
  },
  {
    "name": "department",
    "trans": [],
    "usphone": "",
    "ukphone": ""
  },
  {
    "name": "make a living",
    "trans": [],
    "usphone": "",
    "ukphone": ""
  },
  {
    "name": "solution",
    "trans": [],
    "usphone": "",
    "ukphone": ""
  },
  {
    "name": "port",
    "trans": [],
    "usphone": "",
    "ukphone": ""
  },
  {
    "name": "present",
    "trans": [],
    "usphone": "",
    "ukphone": ""
  },
  {
    "name": "intelligence",
    "trans": [],
    "usphone": "",
    "ukphone": ""
  },
  {
    "name": "intelligent",
    "trans": [],
    "usphone": "",
    "ukphone": ""
  },
  {
    "name": "Iceberg",
    "trans": [],
    "usphone": "",
    "ukphone": ""
  },
  {
    "name": "seal",
    "trans": [],
    "usphone": "",
    "ukphone": ""
  },
  {
    "name": "energetic",
    "trans": [],
    "usphone": "",
    "ukphone": ""
  },
  {
    "name": "penguin",
    "trans": [],
    "usphone": "",
    "ukphone": ""
  },
  {
    "name": "coral",
    "trans": [],
    "usphone": "",
    "ukphone": ""
  },
  {
    "name": "discovery",
    "trans": [],
    "usphone": "",
    "ukphone": ""
  },
  {
    "name": "crab",
    "trans": [],
    "usphone": "",
    "ukphone": ""
  },
  {
    "name": "educate",
    "trans": [],
    "usphone": "",
    "ukphone": ""
  },
  {
    "name": "up-to-date",
    "trans": [],
    "usphone": "",
    "ukphone": ""
  },
  {
    "name": "attraction",
    "trans": [],
    "usphone": "",
    "ukphone": ""
  },
  {
    "name": "attract",
    "trans": [],
    "usphone": "",
    "ukphone": ""
  },
  {
    "name": "watch out",
    "trans": [],
    "usphone": "",
    "ukphone": ""
  },
  {
    "name": "shark",
    "trans": [],
    "usphone": "",
    "ukphone": ""
  },
  {
    "name": "discount",
    "trans": [],
    "usphone": "",
    "ukphone": ""
  },
  {
    "name": "trick",
    "trans": [],
    "usphone": "",
    "ukphone": ""
  },
  {
    "name": "melt",
    "trans": [],
    "usphone": "",
    "ukphone": ""
  },
  {
    "name": "measure",
    "trans": [],
    "usphone": "",
    "ukphone": ""
  },
  {
    "name": "length",
    "trans": [],
    "usphone": "",
    "ukphone": ""
  },
  {
    "name": "schoolboy",
    "trans": [],
    "usphone": "",
    "ukphone": ""
  },
  {
    "name": "centimetre",
    "trans": [],
    "usphone": "",
    "ukphone": ""
  },
  {
    "name": "barrel",
    "trans": [],
    "usphone": "",
    "ukphone": ""
  },
  {
    "name": "whirlpool",
    "trans": [],
    "usphone": "",
    "ukphone": ""
  },
  {
    "name": "horrible",
    "trans": [],
    "usphone": "",
    "ukphone": ""
  },
  {
    "name": "float",
    "trans": [],
    "usphone": "",
    "ukphone": ""
  },
  {
    "name": "terrify",
    "trans": [],
    "usphone": "",
    "ukphone": ""
  },
  {
    "name": "escape",
    "trans": [],
    "usphone": "",
    "ukphone": ""
  },
  {
    "name": "terror",
    "trans": [],
    "usphone": "",
    "ukphone": ""
  },
  {
    "name": "soul",
    "trans": [],
    "usphone": "",
    "ukphone": ""
  },
  {
    "name": "survive",
    "trans": [],
    "usphone": "",
    "ukphone": ""
  },
  {
    "name": "all at once",
    "trans": [],
    "usphone": "",
    "ukphone": ""
  },
  {
    "name": "recover",
    "trans": [],
    "usphone": "",
    "ukphone": ""
  },
  {
    "name": "scream",
    "trans": [],
    "usphone": "",
    "ukphone": ""
  },
  {
    "name": "sink",
    "trans": [],
    "usphone": "",
    "ukphone": ""
  },
  {
    "name": "pick up",
    "trans": [],
    "usphone": "",
    "ukphone": ""
  },
  {
    "name": "unable",
    "trans": [],
    "usphone": "",
    "ukphone": ""
  },
  {
    "name": "recognise",
    "trans": [],
    "usphone": "",
    "ukphone": ""
  },
  {
    "name": "Oceania",
    "trans": [],
    "usphone": "",
    "ukphone": ""
  },
  {
    "name": "opposite",
    "trans": [],
    "usphone": "",
    "ukphone": ""
  },
  {
    "name": "net",
    "trans": [],
    "usphone": "",
    "ukphone": ""
  },
  {
    "name": "leak",
    "trans": [],
    "usphone": "",
    "ukphone": ""
  },
  {
    "name": "stadium",
    "trans": [],
    "usphone": "",
    "ukphone": ""
  },
  {
    "name": "debate",
    "trans": [],
    "usphone": "",
    "ukphone": ""
  },
  {
    "name": "local",
    "trans": [],
    "usphone": "",
    "ukphone": ""
  },
  {
    "name": "shopkeeper",
    "trans": [],
    "usphone": "",
    "ukphone": ""
  },
  {
    "name": "bay",
    "trans": [],
    "usphone": "",
    "ukphone": ""
  },
  {
    "name": "wildlife",
    "trans": [],
    "usphone": "",
    "ukphone": ""
  },
  {
    "name": "disagree",
    "trans": [],
    "usphone": "",
    "ukphone": ""
  },
  {
    "name": "adventure",
    "trans": [],
    "usphone": "",
    "ukphone": ""
  },
  {
    "name": "desert",
    "trans": [],
    "usphone": "",
    "ukphone": ""
  },
  {
    "name": "canoe",
    "trans": [],
    "usphone": "",
    "ukphone": ""
  },
  {
    "name": "safari",
    "trans": [],
    "usphone": "",
    "ukphone": ""
  },
  {
    "name": "hike",
    "trans": [],
    "usphone": "",
    "ukphone": ""
  },
  {
    "name": "take off",
    "trans": [],
    "usphone": "",
    "ukphone": ""
  },
  {
    "name": "presenter",
    "trans": [],
    "usphone": "",
    "ukphone": ""
  },
  {
    "name": "major",
    "trans": [],
    "usphone": "",
    "ukphone": ""
  },
  {
    "name": "wild",
    "trans": [],
    "usphone": "",
    "ukphone": ""
  },
  {
    "name": "tiring",
    "trans": [],
    "usphone": "",
    "ukphone": ""
  },
  {
    "name": "raft",
    "trans": [],
    "usphone": "",
    "ukphone": ""
  },
  {
    "name": "extra",
    "trans": [],
    "usphone": "",
    "ukphone": ""
  },
  {
    "name": "optional",
    "trans": [],
    "usphone": "",
    "ukphone": ""
  },
  {
    "name": "horizon",
    "trans": [],
    "usphone": "",
    "ukphone": ""
  },
  {
    "name": "organization",
    "trans": [],
    "usphone": "",
    "ukphone": ""
  },
  {
    "name": "uncomfortable",
    "trans": [],
    "usphone": "",
    "ukphone": ""
  },
  {
    "name": "route",
    "trans": [],
    "usphone": "",
    "ukphone": ""
  },
  {
    "name": "porter",
    "trans": [],
    "usphone": "",
    "ukphone": ""
  },
  {
    "name": "luggage",
    "trans": [],
    "usphone": "",
    "ukphone": ""
  },
  {
    "name": "accommodation",
    "trans": [],
    "usphone": "",
    "ukphone": ""
  },
  {
    "name": "hostel",
    "trans": [],
    "usphone": "",
    "ukphone": ""
  },
  {
    "name": "maximum",
    "trans": [],
    "usphone": "",
    "ukphone": ""
  },
  {
    "name": "altitude",
    "trans": [],
    "usphone": "",
    "ukphone": ""
  },
  {
    "name": "right now",
    "trans": [],
    "usphone": "",
    "ukphone": ""
  },
  {
    "name": "differ",
    "trans": [],
    "usphone": "",
    "ukphone": ""
  },
  {
    "name": "footprint",
    "trans": [],
    "usphone": "",
    "ukphone": ""
  },
  {
    "name": "anxious",
    "trans": [],
    "usphone": "",
    "ukphone": ""
  },
  {
    "name": "extreme",
    "trans": [],
    "usphone": "",
    "ukphone": ""
  },
  {
    "name": "bungee jumping",
    "trans": [],
    "usphone": "",
    "ukphone": ""
  },
  {
    "name": "snowboarding",
    "trans": [],
    "usphone": "",
    "ukphone": ""
  },
  {
    "name": "snow rafting",
    "trans": [],
    "usphone": "",
    "ukphone": ""
  },
  {
    "name": "in order to do something",
    "trans": [],
    "usphone": "",
    "ukphone": ""
  },
  {
    "name": "gymnastics",
    "trans": [],
    "usphone": "",
    "ukphone": ""
  },
  {
    "name": "similarity",
    "trans": [],
    "usphone": "",
    "ukphone": ""
  },
  {
    "name": "upside down",
    "trans": [],
    "usphone": "",
    "ukphone": ""
  },
  {
    "name": "exactly",
    "trans": [],
    "usphone": "",
    "ukphone": ""
  },
  {
    "name": "risk",
    "trans": [],
    "usphone": "",
    "ukphone": ""
  },
  {
    "name": "excitement",
    "trans": [],
    "usphone": "",
    "ukphone": ""
  },
  {
    "name": "various",
    "trans": [],
    "usphone": "",
    "ukphone": ""
  },
  {
    "name": "flow",
    "trans": [],
    "usphone": "",
    "ukphone": ""
  },
  {
    "name": "equipment",
    "trans": [],
    "usphone": "",
    "ukphone": ""
  },
  {
    "name": "dull",
    "trans": [],
    "usphone": "",
    "ukphone": ""
  },
  {
    "name": "preference",
    "trans": [],
    "usphone": "",
    "ukphone": ""
  },
  {
    "name": "turn up",
    "trans": [],
    "usphone": "",
    "ukphone": ""
  },
  {
    "name": "back out",
    "trans": [],
    "usphone": "",
    "ukphone": ""
  },
  {
    "name": "get across",
    "trans": [],
    "usphone": "",
    "ukphone": ""
  },
  {
    "name": "jog",
    "trans": [],
    "usphone": "",
    "ukphone": ""
  },
  {
    "name": "traveller",
    "trans": [],
    "usphone": "",
    "ukphone": ""
  },
  {
    "name": "emperor",
    "trans": [],
    "usphone": "",
    "ukphone": ""
  },
  {
    "name": "court",
    "trans": [],
    "usphone": "",
    "ukphone": ""
  },
  {
    "name": "in turn",
    "trans": [],
    "usphone": "",
    "ukphone": ""
  },
  {
    "name": "amaze",
    "trans": [],
    "usphone": "",
    "ukphone": ""
  },
  {
    "name": "goods",
    "trans": [],
    "usphone": "",
    "ukphone": ""
  },
  {
    "name": "confuse",
    "trans": [],
    "usphone": "",
    "ukphone": ""
  },
  {
    "name": "fuel",
    "trans": [],
    "usphone": "",
    "ukphone": ""
  },
  {
    "name": "wealthy",
    "trans": [],
    "usphone": "",
    "ukphone": ""
  },
  {
    "name": "break out",
    "trans": [],
    "usphone": "",
    "ukphone": ""
  },
  {
    "name": "put...into prison",
    "trans": [],
    "usphone": "",
    "ukphone": ""
  },
  {
    "name": "author",
    "trans": [],
    "usphone": "",
    "ukphone": ""
  },
  {
    "name": "dictation",
    "trans": [],
    "usphone": "",
    "ukphone": ""
  },
  {
    "name": "stand by",
    "trans": [],
    "usphone": "",
    "ukphone": ""
  },
  {
    "name": "statement",
    "trans": [],
    "usphone": "",
    "ukphone": ""
  },
  {
    "name": "quantity",
    "trans": [],
    "usphone": "",
    "ukphone": ""
  },
  {
    "name": "professor",
    "trans": [],
    "usphone": "",
    "ukphone": ""
  },
  {
    "name": "hunter",
    "trans": [],
    "usphone": "",
    "ukphone": ""
  },
  {
    "name": "skin",
    "trans": [],
    "usphone": "",
    "ukphone": ""
  },
  {
    "name": "the Antarctic.",
    "trans": [],
    "usphone": "",
    "ukphone": ""
  },
  {
    "name": "on one's way",
    "trans": [],
    "usphone": "",
    "ukphone": ""
  },
  {
    "name": "Norwegian",
    "trans": [],
    "usphone": "",
    "ukphone": ""
  },
  {
    "name": "preparation",
    "trans": [],
    "usphone": "",
    "ukphone": ""
  },
  {
    "name": "sledge",
    "trans": [],
    "usphone": "",
    "ukphone": ""
  },
  {
    "name": "break down",
    "trans": [],
    "usphone": "",
    "ukphone": ""
  },
  {
    "name": "shock",
    "trans": [],
    "usphone": "",
    "ukphone": ""
  },
  {
    "name": "goal",
    "trans": [],
    "usphone": "",
    "ukphone": ""
  },
  {
    "name": "ambition",
    "trans": [],
    "usphone": "",
    "ukphone": ""
  },
  {
    "name": "exhausted",
    "trans": [],
    "usphone": "",
    "ukphone": ""
  },
  {
    "name": "run out of",
    "trans": [],
    "usphone": "",
    "ukphone": ""
  },
  {
    "name": "hopeless",
    "trans": [],
    "usphone": "",
    "ukphone": ""
  },
  {
    "name": "cheerful",
    "trans": [],
    "usphone": "",
    "ukphone": ""
  },
  {
    "name": "distant",
    "trans": [],
    "usphone": "",
    "ukphone": ""
  },
  {
    "name": "carry on",
    "trans": [],
    "usphone": "",
    "ukphone": ""
  },
  {
    "name": "within",
    "trans": [],
    "usphone": "",
    "ukphone": ""
  },
  {
    "name": "sadness",
    "trans": [],
    "usphone": "",
    "ukphone": ""
  },
  {
    "name": "function",
    "trans": [],
    "usphone": "",
    "ukphone": ""
  },
  {
    "name": "patience",
    "trans": [],
    "usphone": "",
    "ukphone": ""
  },
  {
    "name": "nationality",
    "trans": [],
    "usphone": "",
    "ukphone": ""
  },
  {
    "name": "aim",
    "trans": [],
    "usphone": "",
    "ukphone": ""
  },
  {
    "name": "Arctic",
    "trans": [],
    "usphone": "",
    "ukphone": ""
  },
  {
    "name": "transport",
    "trans": [],
    "usphone": "",
    "ukphone": ""
  },
  {
    "name": "observe",
    "trans": [],
    "usphone": "",
    "ukphone": ""
  },
  {
    "name": "disadvantage",
    "trans": [],
    "usphone": "",
    "ukphone": ""
  },
  {
    "name": "staff",
    "trans": [],
    "usphone": "",
    "ukphone": ""
  },
  {
    "name": "survival",
    "trans": [],
    "usphone": "",
    "ukphone": ""
  },
  {
    "name": "shelter",
    "trans": [],
    "usphone": "",
    "ukphone": ""
  },
  {
    "name": "philosophy",
    "trans": [],
    "usphone": "",
    "ukphone": ""
  },
  {
    "name": "limit",
    "trans": [],
    "usphone": "",
    "ukphone": ""
  },
  {
    "name": "ferry",
    "trans": [],
    "usphone": "",
    "ukphone": ""
  },
  {
    "name": "minibus",
    "trans": [],
    "usphone": "",
    "ukphone": ""
  },
  {
    "name": "cyclist",
    "trans": [],
    "usphone": "",
    "ukphone": ""
  },
  {
    "name": "motorist",
    "trans": [],
    "usphone": "",
    "ukphone": ""
  },
  {
    "name": "pedestrian",
    "trans": [],
    "usphone": "",
    "ukphone": ""
  },
  {
    "name": "jam",
    "trans": [],
    "usphone": "",
    "ukphone": ""
  },
  {
    "name": "traffic jam",
    "trans": [],
    "usphone": "",
    "ukphone": ""
  },
  {
    "name": "actually",
    "trans": [],
    "usphone": "",
    "ukphone": ""
  },
  {
    "name": "benefit",
    "trans": [],
    "usphone": "",
    "ukphone": ""
  },
  {
    "name": "flat",
    "trans": [],
    "usphone": "",
    "ukphone": ""
  },
  {
    "name": "therefore",
    "trans": [],
    "usphone": "",
    "ukphone": ""
  },
  {
    "name": "convenient",
    "trans": [],
    "usphone": "",
    "ukphone": ""
  },
  {
    "name": "parking",
    "trans": [],
    "usphone": "",
    "ukphone": ""
  },
  {
    "name": "convenience",
    "trans": [],
    "usphone": "",
    "ukphone": ""
  },
  {
    "name": "hopeful",
    "trans": [],
    "usphone": "",
    "ukphone": ""
  },
  {
    "name": "neighbourhood",
    "trans": [],
    "usphone": "",
    "ukphone": ""
  },
  {
    "name": "wherever",
    "trans": [],
    "usphone": "",
    "ukphone": ""
  },
  {
    "name": "thief",
    "trans": [],
    "usphone": "",
    "ukphone": ""
  },
  {
    "name": "chip",
    "trans": [],
    "usphone": "",
    "ukphone": ""
  },
  {
    "name": "insert",
    "trans": [],
    "usphone": "",
    "ukphone": ""
  },
  {
    "name": "indeed",
    "trans": [],
    "usphone": "",
    "ukphone": ""
  },
  {
    "name": "fed up",
    "trans": [],
    "usphone": "",
    "ukphone": ""
  },
  {
    "name": "consequence",
    "trans": [],
    "usphone": "",
    "ukphone": ""
  },
  {
    "name": "arrest",
    "trans": [],
    "usphone": "",
    "ukphone": ""
  },
  {
    "name": "bone",
    "trans": [],
    "usphone": "",
    "ukphone": ""
  },
  {
    "name": "work out",
    "trans": [],
    "usphone": "",
    "ukphone": ""
  },
  {
    "name": "argue",
    "trans": [],
    "usphone": "",
    "ukphone": ""
  },
  {
    "name": "baggage",
    "trans": [],
    "usphone": "",
    "ukphone": ""
  },
  {
    "name": "platform",
    "trans": [],
    "usphone": "",
    "ukphone": ""
  },
  {
    "name": "belt",
    "trans": [],
    "usphone": "",
    "ukphone": ""
  },
  {
    "name": "ambassador",
    "trans": [],
    "usphone": "",
    "ukphone": ""
  },
  {
    "name": "sensitive",
    "trans": [],
    "usphone": "",
    "ukphone": ""
  },
  {
    "name": "grey",
    "trans": [],
    "usphone": "",
    "ukphone": ""
  },
  {
    "name": "gentle",
    "trans": [],
    "usphone": "",
    "ukphone": ""
  },
  {
    "name": "fierce",
    "trans": [],
    "usphone": "",
    "ukphone": ""
  },
  {
    "name": "vocabulary",
    "trans": [],
    "usphone": "",
    "ukphone": ""
  },
  {
    "name": "interpreter",
    "trans": [],
    "usphone": "",
    "ukphone": ""
  },
  {
    "name": "schedule",
    "trans": [],
    "usphone": "",
    "ukphone": ""
  },
  {
    "name": "timetable",
    "trans": [],
    "usphone": "",
    "ukphone": ""
  },
  {
    "name": "foolish",
    "trans": [],
    "usphone": "",
    "ukphone": ""
  },
  {
    "name": "responsibility",
    "trans": [],
    "usphone": "",
    "ukphone": ""
  },
  {
    "name": "rely on",
    "trans": [],
    "usphone": "",
    "ukphone": ""
  },
  {
    "name": "hostess",
    "trans": [],
    "usphone": "",
    "ukphone": ""
  },
  {
    "name": "air hostess",
    "trans": [],
    "usphone": "",
    "ukphone": ""
  },
  {
    "name": "non-smoking",
    "trans": [],
    "usphone": "",
    "ukphone": ""
  },
  {
    "name": "case",
    "trans": [],
    "usphone": "",
    "ukphone": ""
  },
  {
    "name": "suitcase",
    "trans": [],
    "usphone": "",
    "ukphone": ""
  },
  {
    "name": "pull up",
    "trans": [],
    "usphone": "",
    "ukphone": ""
  },
  {
    "name": "pull out",
    "trans": [],
    "usphone": "",
    "ukphone": ""
  },
  {
    "name": "content",
    "trans": [],
    "usphone": "",
    "ukphone": ""
  },
  {
    "name": "petrol",
    "trans": [],
    "usphone": "",
    "ukphone": ""
  },
  {
    "name": "gas",
    "trans": [],
    "usphone": "",
    "ukphone": ""
  },
  {
    "name": "solar",
    "trans": [],
    "usphone": "",
    "ukphone": ""
  },
  {
    "name": "racer",
    "trans": [],
    "usphone": "",
    "ukphone": ""
  },
  {
    "name": "sunlight",
    "trans": [],
    "usphone": "",
    "ukphone": ""
  },
  {
    "name": "kindergarten",
    "trans": [],
    "usphone": "",
    "ukphone": ""
  },
  {
    "name": "so far",
    "trans": [],
    "usphone": "",
    "ukphone": ""
  },
  {
    "name": "take place",
    "trans": [],
    "usphone": "",
    "ukphone": ""
  },
  {
    "name": "northwest",
    "trans": [],
    "usphone": "",
    "ukphone": ""
  },
  {
    "name": "southeast",
    "trans": [],
    "usphone": "",
    "ukphone": ""
  },
  {
    "name": "chapter",
    "trans": [],
    "usphone": "",
    "ukphone": ""
  },
  {
    "name": "impression",
    "trans": [],
    "usphone": "",
    "ukphone": ""
  },
  {
    "name": "reliable",
    "trans": [],
    "usphone": "",
    "ukphone": ""
  },
  {
    "name": "golf",
    "trans": [],
    "usphone": "",
    "ukphone": ""
  },
  {
    "name": "operator",
    "trans": [],
    "usphone": "",
    "ukphone": ""
  },
  {
    "name": "appreciate",
    "trans": [],
    "usphone": "",
    "ukphone": ""
  },
  {
    "name": "essay",
    "trans": [],
    "usphone": "",
    "ukphone": ""
  },
  {
    "name": "shopping",
    "trans": [],
    "usphone": "",
    "ukphone": ""
  },
  {
    "name": "carbon monoxide",
    "trans": [],
    "usphone": "",
    "ukphone": ""
  },
  {
    "name": "highway",
    "trans": [],
    "usphone": "",
    "ukphone": ""
  },
  {
    "name": "construction",
    "trans": [],
    "usphone": "",
    "ukphone": ""
  },
  {
    "name": "pavement",
    "trans": [],
    "usphone": "",
    "ukphone": ""
  },
  {
    "name": "crossroads",
    "trans": [],
    "usphone": "",
    "ukphone": ""
  },
  {
    "name": "amount",
    "trans": [],
    "usphone": "",
    "ukphone": ""
  },
  {
    "name": "physical",
    "trans": [],
    "usphone": "",
    "ukphone": ""
  },
  {
    "name": "motor",
    "trans": [],
    "usphone": "",
    "ukphone": ""
  },
  {
    "name": "figure",
    "trans": [],
    "usphone": "",
    "ukphone": ""
  },
  {
    "name": "go up",
    "trans": [],
    "usphone": "",
    "ukphone": ""
  },
  {
    "name": "engine",
    "trans": [],
    "usphone": "",
    "ukphone": ""
  },
  {
    "name": "per",
    "trans": [],
    "usphone": "",
    "ukphone": ""
  },
  {
    "name": "centigrade",
    "trans": [],
    "usphone": "",
    "ukphone": ""
  },
  {
    "name": "admit",
    "trans": [],
    "usphone": "",
    "ukphone": ""
  },
  {
    "name": "addicted",
    "trans": [],
    "usphone": "",
    "ukphone": ""
  },
  {
    "name": "on average",
    "trans": [],
    "usphone": "",
    "ukphone": ""
  },
  {
    "name": "occupy",
    "trans": [],
    "usphone": "",
    "ukphone": ""
  },
  {
    "name": "somehow",
    "trans": [],
    "usphone": "",
    "ukphone": ""
  },
  {
    "name": "whichever",
    "trans": [],
    "usphone": "",
    "ukphone": ""
  },
  {
    "name": "suit",
    "trans": [],
    "usphone": "",
    "ukphone": ""
  },
  {
    "name": "damage",
    "trans": [],
    "usphone": "",
    "ukphone": ""
  },
  {
    "name": "nowhere",
    "trans": [],
    "usphone": "",
    "ukphone": ""
  },
  {
    "name": "crossing",
    "trans": [],
    "usphone": "",
    "ukphone": ""
  },
  {
    "name": "tunnel",
    "trans": [],
    "usphone": "",
    "ukphone": ""
  },
  {
    "name": "plus",
    "trans": [],
    "usphone": "",
    "ukphone": ""
  },
  {
    "name": "frequent",
    "trans": [],
    "usphone": "",
    "ukphone": ""
  },
  {
    "name": "fare",
    "trans": [],
    "usphone": "",
    "ukphone": ""
  }
]