{
  "id": "ieltsWang4",
  "name": "雅思wang C4",
  "description": "雅思听力形容词副词语料库",
  "category": "国际考试",
  "tags": [
    "IELTS"
  ],
  "url": "IELTS_WANG_4.json",
  "length": 346,
  "translateLanguage": "common",
  "language": "en",
  "type": "word",
  "words": [
    "abnormal",
    "academic",
    "accessible",
    "accountable",
    "accurate",
    "additional",
    "adequate",
    "advanced",
    "advisable",
    "allergic",
    "alternative",
    "amazing",
    "ambiguous",
    "ambitious",
    "analytical",
    "ancient",
    "angry",
    "applied",
    "archaeological",
    "artificial",
    "artistic",
    "ascending",
    "atmospheric",
    "attentive",
    "audio",
    "available",
    "aware",
    "awful",
    "auto",
    "bald",
    "barren",
    "basic",
    "beautiful",
    "biological",
    "blind",
    "blond",
    "British",
    "broad",
    "buried",
    "calculating",
    "casual",
    "central",
    "challenging",
    "cheaper",
    "cheerful",
    "children's",
    "classical",
    "clean",
    "cleanest",
    "clear",
    "clever",
    "coastal",
    "comfortable",
    "common",
    "commonsense",
    "complete",
    "completed",
    "confident",
    "conservative",
    "convenient",
    "co-operative",
    "corrupt",
    "costly",
    "cream",
    "critical",
    "crucial",
    "cultural",
    "curly",
    "current",
    "daily",
    "dairy",
    "dangerous",
    "dark",
    "departmental",
    "dependent",
    "detailed",
    "different",
    "direct",
    "disabled",
    "distant",
    "distinct",
    "domestic",
    "dominant",
    "eastern",
    "economic",
    "educational",
    "effective",
    "efficient",
    "elementary",
    "empty",
    "enormous",
    "enthusiastic",
    "environmental",
    "essential",
    "excited",
    "exciting",
    "existent",
    "expensive",
    "experienced",
    "experimental",
    "extensive",
    "extra",
    "fair",
    "fake",
    "famed",
    "familiar",
    "famous",
    "fancy",
    "fashionable",
    "favourite",
    "final",
    "financial",
    "fine",
    "firm",
    "flexible",
    "foreign",
    "formal",
    "former",
    "free",
    "frequent",
    "fundamental",
    "further",
    "general",
    "genetic",
    "geographical",
    "global",
    "handy",
    "harmful",
    "hazardous",
    "healthy",
    "heavier",
    "heavy",
    "helpful",
    "herbivorous",
    "higher",
    "highly-trained",
    "historical",
    "least",
    "ill",
    "illegal",
    "immune",
    "important",
    "impossible",
    "inaccurate",
    "inadequate",
    "individual",
    "industrial",
    "informative",
    "initial",
    "inspiring",
    "intact",
    "intelligent",
    "intensive",
    "interesting",
    "intermediate",
    "internal",
    "international",
    "irregular",
    "irritable",
    "isolated",
    "key",
    "latest",
    "legal",
    "little-known",
    "loyal",
    "magic",
    "magical",
    "magnificent",
    "major",
    "martial",
    "mature",
    "medical",
    "mental",
    "mid",
    "migratory",
    "military",
    "miserable",
    "mobile",
    "moderate",
    "modern",
    "musical",
    "natural",
    "negative",
    "neighbouring",
    "nervous",
    "noble",
    "noisy",
    "non-active",
    "normal",
    "northern",
    "objective",
    "occupational",
    "Olympic",
    "optic",
    "optional",
    "oral",
    "organic",
    "overall",
    "overhead",
    "overseas",
    "parental",
    "payable",
    "perfect",
    "personal",
    "physical",
    "pleasant",
    "political",
    "pop",
    "popular",
    "positive",
    "possible",
    "potential",
    "practical",
    "precious",
    "predictable",
    "present",
    "previous",
    "printed",
    "private",
    "professional",
    "promising",
    "psychiatric",
    "psychological",
    "public",
    "pure",
    "purest",
    "Queen's",
    "random",
    "rapid",
    "rare",
    "raw",
    "recycled",
    "redundant",
    "regional",
    "regular",
    "reinforced",
    "related",
    "relevant",
    "reliable",
    "remote",
    "resistant",
    "reverse",
    "rising",
    "royal",
    "rural",
    "sacked",
    "safe",
    "satisfactory",
    "scarce",
    "scientific",
    "seasonal",
    "seasoned",
    "secondary",
    "second-hand",
    "self-funded",
    "self-sufficient",
    "senior",
    "sensible",
    "serial",
    "serious",
    "seven-screen",
    "several",
    "shared",
    "sharp",
    "short",
    "sick",
    "silent",
    "silver",
    "similar",
    "simple",
    "sleepy",
    "slim",
    "smart",
    "smelly",
    "social",
    "solar",
    "soundproof",
    "southern",
    "spacious",
    "spare",
    "special",
    "specialised",
    "species",
    "specific",
    "spiral",
    "stable",
    "steady",
    "stout",
    "strained",
    "stressful",
    "stretching",
    "strong",
    "stronger",
    "subjective",
    "successful",
    "sufficient",
    "suitable",
    "super",
    "surprised",
    "systematic",
    "technical",
    "theoretical",
    "traditional",
    "troublesome",
    "typical",
    "unanimous",
    "uncomfortable",
    "unconvincing",
    "underground",
    "unfair",
    "unhealthy",
    "unique",
    "united",
    "unreliable",
    "unsocial",
    "unusual",
    "useful",
    "useless",
    "usual",
    "various",
    "violent",
    "virtual",
    "visible",
    "visual",
    "warm",
    "washable",
    "wealthy",
    "weekly",
    "western",
    "whole",
    "wide",
    "wise",
    "worthwhile",
    "worthy",
    "almost",
    "currently",
    "directly",
    "effectively",
    "efficiently",
    "originally",
    "physically",
    "professionally",
    "rapidly",
    "regularly",
    "scarcely",
    "virtually"
  ]
}