{
  "id": "PEPGaoZhong_6",
  "name": "高中必修6",
  "description": "人教版高中英语-必修 6",
  "url": "PEPGaoZhong_6.json",
  "length": 391,
  "category": "青少年英语",
  "tags": [
    "高中",
    "人教版"
  ],
  "translateLanguage": "common",
  "language": "en",
  "type": "word",
  "words": [
    "realistic",
    "abstract",
    "sculpture",
    "sculptor",
    "gallery",
    "faith",
    "faithfully",
    "consequently",
    "aim",
    "conventional",
    "typical",
    "evident",
    "Giotto di Bondone",
    "renaissance",
    "the Renaissance",
    "adopt",
    "humanistic",
    "possess",
    "possession",
    "superb",
    "perspective",
    "technique",
    "Masaccio",
    "coincidence",
    "by coincidence",
    "masterpiece",
    "impressionism",
    "impressionist",
    "post-impressionist",
    "a great deal",
    "shadow",
    "ridiculous",
    "controversial",
    "attempt",
    "on the other hand",
    "predict",
    "landscape",
    "specific",
    "figure",
    "clay",
    "critic",
    "bronze",
    "marble",
    "Mona Lisa",
    "Leonardo da Vinci",
    "carve",
    "delicate",
    "Michelangelo",
    "canvas",
    "Picasso",
    "cafe",
    "allergic",
    "effectively",
    "exhibition",
    "aggressive",
    "scholar",
    "flesh",
    "in the flesh",
    "Matisse",
    "geometry",
    "bunch",
    "Manhattan",
    "avenue",
    "preference",
    "Guggenheim  Museum",
    "display",
    "appeal",
    "appeal to",
    "fragile",
    "circular",
    "metropolitan",
    "reputation",
    "civilization",
    "Egypt",
    "Egyptian",
    "visual",
    "fragrant",
    "Monet",
    "Whitney",
    "Madison",
    "contemporary",
    "permanent",
    "district",
    "committee",
    "signature",
    "poetry",
    "tick",
    "rhyme",
    "convey",
    "emotion",
    "nursery",
    "nursery rhyme",
    "concrete",
    "repetition",
    "contradictory",
    "hush",
    "mockingbird",
    "diamond",
    "brass",
    "billy-goat",
    "flexible",
    "pattern",
    "squire",
    "cottage",
    "coffin",
    "sparrow",
    "kitten",
    "take it easy",
    "run out of",
    "cinquain",
    "be made up of",
    "tease",
    "salty",
    "droop",
    "dread",
    "endless",
    "haiku",
    "syllable",
    "minimum",
    "translation",
    "branch",
    "melt",
    "brimful",
    "in particular",
    "eventually",
    "await",
    "transform",
    "revolve",
    "utter",
    "sorrow",
    "bare",
    "librarian",
    "forever",
    "stem",
    "cement",
    "section",
    "appropriate",
    "exchange",
    "diploma",
    "sponsor",
    "blank",
    "compass",
    "bride",
    "bridegroom",
    "championship",
    "rhythmic",
    "darkness",
    "warmth",
    "try out",
    "scholarship",
    "pianist",
    "violinist",
    "let out",
    "load",
    "cigarette",
    "alcohol",
    "alcoholic",
    "abuse",
    "fitness",
    "sexual",
    "stress",
    "stressful",
    "obesity",
    "adolescent",
    "adolescence",
    "ban",
    "due",
    "due to",
    "tough",
    "addicted",
    "addicted to",
    "nicotine",
    "accustom",
    "accustomed",
    "accustomed to",
    "withdrawal",
    "bad-tempered",
    "automatic",
    "automatically",
    "mental",
    "mentally",
    "quit",
    "effect",
    "lung",
    "pregnant",
    "abnormal",
    "breathless",
    "unfit",
    "strengthen",
    "resolve",
    "decide on",
    "packet",
    "feel like",
    "feel like doing",
    "relaxation",
    "desperate",
    "chemist",
    "gum",
    "chewing gum",
    "disappointed",
    "weaken",
    "ashamed",
    "comprehension",
    "in spite of",
    "take risks",
    "take a risk",
    "get into",
    "etc",
    "appendix",
    "illegal",
    "pill",
    "robbery",
    "slippery",
    "HIV",
    "AIDS",
    "at risk",
    "SARS",
    "immune",
    "survival",
    "sex",
    "fluid",
    "inject",
    "injection",
    "needle",
    "spill",
    "male",
    "female",
    "condom",
    "homosexual",
    "prejudice",
    "judgement",
    "disco",
    "abortion",
    "cigar",
    "embarrassed",
    "awkward",
    "consume",
    "renewable",
    "greenhouse",
    "Fahrenheit",
    "come about",
    "Sophie",
    "Armstrong",
    "graph",
    "random",
    "phenomenon",
    "subscribe",
    "subscribe to",
    "fossil",
    "fuel",
    "byproduct",
    "Janice",
    "Foster",
    "methane",
    "Celsius",
    "quantity",
    "quantities of",
    "tend",
    "go up",
    "Charles Keeling",
    "measurement",
    "per",
    "data",
    "result in",
    "trend",
    "catastrophe",
    "flood",
    "drought",
    "famine",
    "George Hambley",
    "oppose",
    "opposed",
    "be opposed to",
    "mild",
    "environmental",
    "environmentalist",
    "consequence",
    "state",
    "range",
    "even if",
    "keep on",
    "glance",
    "steady",
    "steadily",
    "tendency",
    "widespread",
    "on the whole",
    "economical",
    "hectare",
    "average",
    "existence",
    "outer",
    "on behalf of",
    "individual",
    "advocate",
    "commitment",
    "put up with",
    "pollution",
    "growth",
    "electrical",
    "appliance",
    "so long as",
    "casual",
    "and so on",
    "motor",
    "can",
    "circumstance",
    "microwave",
    "refresh",
    "educator",
    "contribution",
    "imperative",
    "heading",
    "slogan",
    "presentation",
    "nuclear",
    "disagreement",
    "diagram",
    "volcano",
    "volcanic",
    "volcanology",
    "volcanologist",
    "erupt",
    "eruption",
    "ash",
    "crater",
    "lava",
    "hurricane",
    "questionnaire",
    "alongside",
    "equipment",
    "appoint",
    "observatory",
    "database",
    "Mount  Kilauea",
    "evaluate",
    "burn to the ground",
    "wave",
    "molten",
    "fountain",
    "absolute",
    "absolutely",
    "spaceman",
    "suit",
    "helmet",
    "boot",
    "make one’s way",
    "potential",
    "actual",
    "geology",
    "Mount Etna",
    "Sicily",
    "sample",
    "candidate",
    "Mount Vesuvius",
    "threat",
    "bungalow",
    "Pompeii",
    "tornado",
    "typhoon",
    "thunderstorm",
    "precious",
    "novelist",
    "fog",
    "document",
    "rainbow",
    "uncomfortable",
    "balcony",
    "unconscious",
    "shoot",
    "shot",
    "tremble",
    "sweat",
    "anxious",
    "anxiety",
    "panic",
    "tsunami",
    "glance through",
    "Manchu",
    "vary from…to…",
    "diverse",
    "diversity",
    "crane",
    "leopard",
    "spectacular",
    "bathe",
    "arouse",
    "appreciation",
    "peak",
    "persuasion",
    "guarantee"
  ]
}